{
  "name": "flow-03",
  "type": "registry:component",
  "description": "Full-width ribbon of rotating capability words with blur-crossfade morphs and a continuously flowing gradient underline.",
  "dependencies": [
    "framer-motion"
  ],
  "registryDependencies": [],
  "files": [
    {
      "type": "registry:component",
      "content": "\"use client\";\n\nimport React, { useEffect, useState } from \"react\";\nimport { AnimatePresence, motion } from \"framer-motion\";\nimport { cn } from \"@/lib/utils\";\n\nexport interface Flow_03Props {\n  /** Static lead-in before the rotating word. */\n  prefix?: string;\n  /** Capability words that rotate through the ribbon. */\n  words?: string[];\n  /** Mono microcopy line under the ribbon. */\n  microcopy?: string;\n  /** Milliseconds each word stays on screen. */\n  interval?: number;\n  className?: string;\n}\n\nconst defaultWords = [\"Dictate\", \"Compose\", \"Translate\", \"Summarize\", \"Rewrite\"];\n\nconst Flow_03 = ({\n  prefix = \"Speak to\",\n  words = defaultWords,\n  microcopy = \"voice → text · 62 languages · 3× faster than typing\",\n  interval = 2200,\n  className,\n}: Flow_03Props) => {\n  const [index, setIndex] = useState(0);\n\n  useEffect(() => {\n    const id = setInterval(\n      () => setIndex((i) => (i + 1) % words.length),\n      interval\n    );\n    return () => clearInterval(id);\n  }, [words.length, interval]);\n\n  const word = words[index] ?? words[0]!;\n\n  return (\n    <div className={cn(\"w-full max-w-2xl px-2 py-6 text-center\", className)}>\n      <h2 className=\"flex min-h-14 flex-wrap items-baseline justify-center gap-x-3 text-3xl font-semibold tracking-tight text-zinc-900 dark:text-zinc-100 sm:text-4xl\">\n        <span>{prefix}</span>\n        <span className=\"relative inline-flex flex-col items-center\">\n          {/* Rotating word — blur crossfade */}\n          <span className=\"relative grid overflow-visible\">\n            <AnimatePresence mode=\"popLayout\" initial={false}>\n              <motion.span\n                key={word}\n                initial={{ opacity: 0, y: 10, filter: \"blur(8px)\" }}\n                animate={{ opacity: 1, y: 0, filter: \"blur(0px)\" }}\n                exit={{ opacity: 0, y: -10, filter: \"blur(8px)\" }}\n                transition={{ type: \"spring\", stiffness: 350, damping: 30 }}\n                className=\"whitespace-nowrap text-emerald-600 dark:text-emerald-400\"\n              >\n                {word}\n              </motion.span>\n            </AnimatePresence>\n          </span>\n          {/* Flowing gradient underline */}\n          <span\n            aria-hidden\n            className=\"mt-1 block h-[3px] w-full overflow-hidden rounded-full\"\n          >\n            <motion.span\n              className=\"block h-full w-[200%] rounded-full\"\n              style={{\n                backgroundImage:\n                  \"linear-gradient(90deg, rgba(16,185,129,0) 0%, rgba(16,185,129,0.9) 25%, rgba(45,212,191,0.9) 50%, rgba(16,185,129,0.9) 75%, rgba(16,185,129,0) 100%)\",\n              }}\n              animate={{ x: [\"-50%\", \"0%\"] }}\n              transition={{ duration: 2.4, repeat: Infinity, ease: \"linear\" }}\n            />\n          </span>\n        </span>\n        <span>anything.</span>\n      </h2>\n\n      <p className=\"mt-4 font-mono text-[11px] tracking-wide text-zinc-400 dark:text-zinc-500\">\n        {microcopy}\n      </p>\n    </div>\n  );\n};\n\nexport default Flow_03;\n",
      "path": "/src/components/xui/flow/flow-03.tsx",
      "target": "components/xui/flow-03.tsx"
    }
  ]
}